shepherd/__init__.py
shepherd/api.py
shepherd/flock.py
shepherd/imageinfo.py
shepherd/kubeshepherd.py
shepherd/network_pool.py
shepherd/pool.py
shepherd/schema.py
shepherd/shepherd.py
shepherd/wsgi.py
shepherd/static_base/default.css
shepherd/static_base/shepherd-client.bundle.js
shepherd/static_base/ui.js
shepherd/templates/browser_embed.html
shepherd/templates/error.html
shepherd/templates/shepherd.html
shepherd-1.1.0.dist-info/DESCRIPTION.rst
shepherd-1.1.0.dist-info/METADATA
shepherd-1.1.0.dist-info/RECORD
shepherd-1.1.0.dist-info/WHEEL
shepherd-1.1.0.dist-info/entry_points.txt
shepherd-1.1.0.dist-info/metadata.json
shepherd-1.1.0.dist-info/top_level.txt
shepherd-1.1.0.dist-info/zip-safe
